randog/__init__.py
randog/__main__.py
randog/_examples.py
randog/_logging.py
randog/_processmode.py
randog/exceptions.py
randog/rangeutils.py
randog/timedelta_util.py
randog/_main/__init__.py
randog/_main/_logging.py
randog/_main/_main_args.py
randog/_main/_main_func.py
randog/_main/_rnd.py
randog/_main/_warning.py
randog/_main/_subcmd_def/__init__.py
randog/_main/_subcmd_def/_base.py
randog/_main/_subcmd_def/_bool.py
randog/_main/_subcmd_def/_byfile.py
randog/_main/_subcmd_def/_bytes.py
randog/_main/_subcmd_def/_date.py
randog/_main/_subcmd_def/_datetime.py
randog/_main/_subcmd_def/_decimal.py
randog/_main/_subcmd_def/_dice.py
randog/_main/_subcmd_def/_float.py
randog/_main/_subcmd_def/_int.py
randog/_main/_subcmd_def/_ipv4.py
randog/_main/_subcmd_def/_str.py
randog/_main/_subcmd_def/_time.py
randog/_main/_subcmd_def/_timedelta.py
randog/_main/_subcmd_def/fmt_wrapper/__init__.py
randog/_main/_subcmd_def/fmt_wrapper/_base.py
randog/_main/_subcmd_def/fmt_wrapper/bytes.py
randog/_main/_subcmd_def/fmt_wrapper/timedelta.py
randog/_output/__init__.py
randog/_utils/__init__.py
randog/_utils/comp.py
randog/_utils/exceptions.py
randog/_utils/floatutils.py
randog/_utils/linesep.py
randog/_utils/nullsafe.py
randog/_utils/type.py
randog/_utils/formatutils/__init__.py
randog/_utils/formatutils/_bytes.py
randog/_utils/formatutils/_cmn.py
randog/factory/__init__.py
randog/factory/_base.py
randog/factory/_bool.py
randog/factory/_by_callable.py
randog/factory/_by_iterator.py
randog/factory/_bytes.py
randog/factory/_choice.py
randog/factory/_const.py
randog/factory/_date.py
randog/factory/_datetime.py
randog/factory/_decimal.py
randog/factory/_dice.py
randog/factory/_dict.py
randog/factory/_float.py
randog/factory/_from_example.py
randog/factory/_from_pyfile.py
randog/factory/_from_pyfile_config.py
randog/factory/_increment.py
randog/factory/_int.py
randog/factory/_ipv4.py
randog/factory/_list.py
randog/factory/_logging.py
randog/factory/_time.py
randog/factory/_timedelta.py
randog-0.19.0.dist-info/LICENSE
randog-0.19.0.dist-info/METADATA
randog-0.19.0.dist-info/WHEEL
randog-0.19.0.dist-info/entry_points.txt
randog-0.19.0.dist-info/top_level.txt
randog-0.19.0.dist-info/RECORD
