Metadata-Version: 2.1
Name: randog
Version: 0.19.0
Summary: Generate data randomly
Home-page: UNKNOWN
Author: k-izumi
Author-email: k.izumi.ysk@gmail.com
Maintainer: k-izumi
Maintainer-email: k.izumi.ysk@gmail.com
License: MIT
Project-URL: Bug Tracker, https://github.com/unaguna/random-obj-generator/issues
Project-URL: Documentation, https://unaguna.github.io/random-obj-generator/
Project-URL: Source Code, https://github.com/unaguna/random-obj-generator
Platform: UNKNOWN
Classifier: Development Status :: 4 - Beta
Classifier: Programming Language :: Python :: 3
Classifier: Programming Language :: Python :: 3 :: Only
Classifier: Programming Language :: Python :: 3.8
Classifier: Programming Language :: Python :: 3.9
Classifier: Programming Language :: Python :: 3.10
Classifier: Programming Language :: Python :: 3.11
Classifier: Programming Language :: Python :: 3.12
Classifier: Programming Language :: Python :: 3.13
Classifier: License :: OSI Approved :: MIT License
Classifier: Operating System :: POSIX
Classifier: Operating System :: Microsoft :: Windows
Classifier: Topic :: Utilities
